image_processing/__init__.py
image_processing/processing/__init__.py
image_processing/processing/combination.py
image_processing/processing/transformation.py
image_processing/utils/__init__.py
image_processing/utils/io.py
image_processing/utils/plot.py
processamento_imagem_dio_desafio-0.0.1.dist-info/METADATA
processamento_imagem_dio_desafio-0.0.1.dist-info/WHEEL
processamento_imagem_dio_desafio-0.0.1.dist-info/top_level.txt
processamento_imagem_dio_desafio-0.0.1.dist-info/RECORD
