Metadata-Version: 2.1
Name: processamento-imagem-dio-desafio
Version: 0.0.1
Summary: Image Processing Package Using SKimage
Home-page: https://github.com/raifreire/image-processing-package
Author: raifreire
Requires-Python: >=3.5
Requires-Dist: matplotlib
Requires-Dist: numpy
Requires-Dist: scikit-image (>=0.16.1)
